FlashBootstrap/FlashBootstrap.py
FlashBootstrap/Version.py
FlashBootstrap/__init__.py
build/lib/FlashBootstrap/FlashBootstrap.py
build/lib/FlashBootstrap/Version.py
build/lib/FlashBootstrap/__init__.py
build/lib/build/lib/FlashBootstrap/FlashBootstrap.py
build/lib/build/lib/FlashBootstrap/Version.py
build/lib/build/lib/FlashBootstrap/__init__.py
FlashBootstrap-1.0.dist-info/LICENSE
FlashBootstrap-1.0.dist-info/METADATA
FlashBootstrap-1.0.dist-info/WHEEL
FlashBootstrap-1.0.dist-info/top_level.txt
FlashBootstrap-1.0.dist-info/RECORD
