Metadata-Version: 2.1
Name: FlashBootstrap
Version: 1.0
Summary: Store Flash messages in session data until they are retrieved. Bootstrap compatibility, sticky messages, and more.
Home-page: https://github.com/emmamartins/FlashBootstrap
Author: Emmanuel Essien
Author-email: emmaessiensp@gmail.com
Maintainer: Emmanuel Essien
Maintainer-email: emmaessiensp@gmail.com
License: GPL3
Keywords: flash message,boostrap flash,bootstrap pytonik,mvc,oop,module,python,framework,flash,message,web,app,pytonik,web development
Platform: UNKNOWN
Classifier: Environment :: Console
Classifier: Environment :: Web Environment
Classifier: Intended Audience :: Developers
Classifier: License :: OSI Approved :: BSD License
Classifier: Topic :: Office/Business
Classifier: Topic :: Internet :: WWW/HTTP :: Dynamic Content
Classifier: Topic :: Internet :: WWW/HTTP :: WSGI :: Application
Classifier: Topic :: Software Development :: Libraries :: Application Frameworks
Classifier: Topic :: Software Development :: Libraries :: Python Modules
Classifier: Operating System :: OS Independent
Classifier: Programming Language :: Python :: 2.7
Classifier: Programming Language :: Python :: 3
Classifier: Programming Language :: Python :: 3.4
Classifier: Programming Language :: Python :: 3.5
Classifier: Programming Language :: Python :: 3.6
Classifier: Programming Language :: Python :: 3.7
Classifier: Programming Language :: Python :: 3.8
Classifier: Programming Language :: Python :: 3.9
Classifier: Programming Language :: Python
Requires-Python: >=2.7, >=2.7.*, >=3.*
Requires-Dist: pytonik
